CHANGELOG.md
LICENSE
MANIFEST.in
README.md
setup.cfg
setup.py
pip_services3_aws/__init__.py
pip_services3_aws.egg-info/PKG-INFO
pip_services3_aws.egg-info/SOURCES.txt
pip_services3_aws.egg-info/dependency_links.txt
pip_services3_aws.egg-info/requires.txt
pip_services3_aws.egg-info/top_level.txt
pip_services3_aws.egg-info/zip-safe
pip_services3_aws/build/DefaultAwsFactory.py
pip_services3_aws/build/__init__.py
pip_services3_aws/clients/CommandableLambdaClient.py
pip_services3_aws/clients/LambdaClient.py
pip_services3_aws/clients/__init__.py
pip_services3_aws/connect/AwsConnectionParams.py
pip_services3_aws/connect/AwsConnectionResolver.py
pip_services3_aws/connect/__init__.py
pip_services3_aws/containers/CommandableLambdaFunction.py
pip_services3_aws/containers/LambdaFunction.py
pip_services3_aws/containers/__init__.py
pip_services3_aws/count/CloudWatchCounters.py
pip_services3_aws/count/CloudWatchUnit.py
pip_services3_aws/count/__init__.py
pip_services3_aws/log/CloudWatchLogger.py
pip_services3_aws/log/__init__.py
pip_services3_aws/services/CommandableLambdaService.py
pip_services3_aws/services/ILambdaService.py
pip_services3_aws/services/LambdaAction.py
pip_services3_aws/services/LambdaService.py
pip_services3_aws/services/__init__.py
pip_services3_aws/test/TestCommandableLambdaClient.py
pip_services3_aws/test/TestLambdaClient.py
pip_services3_aws/test/__init__.py
test/connect/__init__.py
test/connect/test_AwsConnectionParams.py
test/containers/DummyCommandableLambdaFunction.py
test/containers/DummyLambdaFunction.py
test/containers/__init__.py
test/containers/test_DummyCommandableLambdaFunction.py
test/containers/test_DummyLambdaFunction.py
test/count/CountersFixture.py
test/count/__init__.py
test/count/test_CloudWatchCounters.py
test/log/LoggerFixture.py
test/log/__init__.py
test/log/test_CloudWatchLogger.py
test/services/DummyCommandableLambdaService.py
test/services/DummyLambdaFunction.py
test/services/DummyLambdaService.py
test/services/__init__.py
test/services/test_DummyCommandableLambdaService.py
test/services/test_DummyLambdaService.py